rdj_voting/__init__.py
rdj_voting/__main__.py
rdj_voting/ressources.py
rdj_voting/rdj/__init__.py
rdj_voting/rdj/rdj_song.py
rdj_voting/rdj/rdj_voting.py
rdj_voting_mgs-0.1.0.dist-info/LICENSE
rdj_voting_mgs-0.1.0.dist-info/METADATA
rdj_voting_mgs-0.1.0.dist-info/WHEEL
rdj_voting_mgs-0.1.0.dist-info/top_level.txt
rdj_voting_mgs-0.1.0.dist-info/RECORD
