Metadata-Version: 2.1
Name: rdj-voting-mgs
Version: 0.1.0
Summary: Automatic voting for RDJ
Home-page: https://github.com/TGha/rdj_voting
Author: RAVALISON Tsiorimampionina
Author-email: rtsiori@gmail.com
License: UNKNOWN
Project-URL: Bug Tracker, https://github.com/TGha/rdj_voting/issues
Platform: UNKNOWN
Classifier: Programming Language :: Python :: 3
Classifier: License :: OSI Approved :: GNU General Public License v3 (GPLv3)
Classifier: Operating System :: OS Independent
Requires-Python: >=3.6
License-File: LICENSE
